vessel_validator/__init__.py
vessel_validator/py.typed
vessel_validator/validator.py
vessel_validator-0.1.1.dist-info/licenses/LICENSE
vessel_validator-0.1.1.dist-info/METADATA
vessel_validator-0.1.1.dist-info/WHEEL
vessel_validator-0.1.1.dist-info/top_level.txt
vessel_validator-0.1.1.dist-info/RECORD
