Metadata-Version: 2.4
Name: vessel-validator
Version: 0.1.1
Summary: Professional MMSI and IMO number validator for maritime applications
Author-email: "Scitus Solutions Ltd." <info@scitus.ca>
Maintainer-email: "Scitus Solutions Ltd." <info@scitus.ca>
License-Expression: MIT
Project-URL: Homepage, https://scitus.ca
Project-URL: Documentation, https://github.com/scitus-ca/vessel-validator#readme
Project-URL: Repository, https://github.com/scitus-ca/vessel-validator
Project-URL: Bug Tracker, https://github.com/scitus-ca/vessel-validator/issues
Project-URL: Changelog, https://github.com/scitus-ca/vessel-validator/blob/main/CHANGELOG.md
Keywords: maritime,vessel,MMSI,IMO,validation,shipping,marine,compliance,AIS,ballast water
Classifier: Development Status :: 4 - Beta
Classifier: Intended Audience :: Developers
Classifier: Operating System :: OS Independent
Classifier: Programming Language :: Python :: 3
Classifier: Programming Language :: Python :: 3.8
Classifier: Programming Language :: Python :: 3.9
Classifier: Programming Language :: Python :: 3.10
Classifier: Programming Language :: Python :: 3.11
Classifier: Programming Language :: Python :: 3.12
Classifier: Topic :: Software Development :: Libraries :: Python Modules
Classifier: Topic :: Scientific/Engineering
Classifier: Typing :: Typed
Requires-Python: >=3.8
License-File: LICENSE
Dynamic: license-file
Dynamic: requires-python
